hermitefunction.py
hermite_function-2.0.dist-info/LICENSE
hermite_function-2.0.dist-info/METADATA
hermite_function-2.0.dist-info/WHEEL
hermite_function-2.0.dist-info/top_level.txt
hermite_function-2.0.dist-info/RECORD
